oarepo_model_builder_tests/__init__.py
oarepo_model_builder_tests/conftest_builder.py
oarepo_model_builder_tests/oarepo_model_builder_setup_cfg.py
oarepo_model_builder_tests/test_resource_builder.py
oarepo_model_builder_tests/test_service_builder.py
oarepo_model_builder_tests/utils_builder.py
oarepo_model_builder_tests/datatypes/__init__.py
oarepo_model_builder_tests/datatypes/components.py
oarepo_model_builder_tests/templates/__init__.py
oarepo_model_builder_tests/templates/conftest.py.jinja2
oarepo_model_builder_tests/templates/test_resource.py.jinja2
oarepo_model_builder_tests/templates/test_service.py.jinja2
oarepo_model_builder_tests/templates/utils.py.jinja2
oarepo_model_builder_tests-4.0.12.dist-info/LICENSE
oarepo_model_builder_tests-4.0.12.dist-info/METADATA
oarepo_model_builder_tests-4.0.12.dist-info/WHEEL
oarepo_model_builder_tests-4.0.12.dist-info/entry_points.txt
oarepo_model_builder_tests-4.0.12.dist-info/top_level.txt
oarepo_model_builder_tests-4.0.12.dist-info/RECORD
