Metadata-Version: 2.2
Name: oarepo-model-builder-tests
Version: 4.0.12
License-File: LICENSE
Requires-Dist: oarepo-model-builder>=4.0.3
